setup.py
DSE3_wrapper/__init__.py
DSE3_wrapper/downloader.py
DSE3_wrapper.egg-info/PKG-INFO
DSE3_wrapper.egg-info/SOURCES.txt
DSE3_wrapper.egg-info/dependency_links.txt
DSE3_wrapper.egg-info/requires.txt
DSE3_wrapper.egg-info/top_level.txt