Metadata-Version: 2.4
Name: DSE3_wrapper
Version: 1.0.0
Summary: A package with auto Google Drive data download
Author: Your Name
Requires-Dist: requests
Requires-Dist: py7zr
Dynamic: author
Dynamic: requires-dist
Dynamic: summary
